{
  "_meta": {
    "generated_at": "2026-05-28T15:50:43.806964+00:00",
    "source": "World Bank WDI (api.worldbank.org)",
    "notes": "Most-recent-value per indicator per country. Indicator codes per WDI metadata.",
    "version": "v21"
  },
  "data": {
    "AFE": {
      "FP.CPI.TOTL.ZG": {
        "value": 4.771,
        "year": 2024
      },
      "NY.GDP.PCAP.CD": {
        "value": 1615.396,
        "year": 2024
      },
      "SN.ITK.DEFC.ZS": {
        "value": 26.084,
        "year": 2023
      }
    },
    "AFW": {
      "FP.CPI.TOTL.ZG": {
        "value": 3.608,
        "year": 2024
      },
      "NY.GDP.PCAP.CD": {
        "value": 1411.337,
        "year": 2024
      },
      "SN.ITK.DEFC.ZS": {
        "value": 16.244,
        "year": 2023
      }
    },
    "AFG": {
      "FP.CPI.TOTL.ZG": {
        "value": -6.601,
        "year": 2024
      },
      "SN.ITK.DEFC.ZS": {
        "value": 28.1,
        "year": 2023
      },
      "AG.PRD.FOOD.XD": {
        "value": 111.43,
        "year": 2022
      }
    },
    "ALB": {
      "FP.CPI.TOTL.ZG": {
        "value": 2.216,
        "year": 2024
      },
      "NY.GDP.PCAP.CD": {
        "value": 11377.776,
        "year": 2024
      },
      "SN.ITK.DEFC.ZS": {
        "value": 5.4,
        "year": 2023
      },
      "AG.PRD.FOOD.XD": {
        "value": 105.4,
        "year": 2022
      }
    },
    "DZA": {
      "FP.CPI.TOTL.ZG": {
        "value": 4.046,
        "year": 2024
      },
      "NY.GDP.PCAP.CD": {
        "value": 5752.991,
        "year": 2024
      },
      "SN.ITK.DEFC.ZS": {
        "value": 2.5,
        "year": 2023
      },
      "AG.PRD.FOOD.XD": {
        "value": 111.22,
        "year": 2022
      }
    },
    "AGO": {
      "FP.CPI.TOTL.ZG": {
        "value": 28.24,
        "year": 2024
      },
      "NY.GDP.PCAP.CD": {
        "value": 2665.874,
        "year": 2024
      },
      "SN.ITK.DEFC.ZS": {
        "value": 22.5,
        "year": 2023
      },
      "AG.PRD.FOOD.XD": {
        "value": 124.09,
        "year": 2022
      }
    },
    "ATG": {
      "FP.CPI.TOTL.ZG": {
        "value": 6.199,
        "year": 2024
      },
      "NY.GDP.PCAP.CD": {
        "value": 23542.453,
        "year": 2024
      },
      "AG.PRD.FOOD.XD": {
        "value": 89.95,
        "year": 2022
      }
    },
    "ARG": {
      "FP.CPI.TOTL.ZG": {
        "value": 219.884,
        "year": 2024
      },
      "NY.GDP.PCAP.CD": {
        "value": 13969.784,
        "year": 2024
      },
      "SN.ITK.DEFC.ZS": {
        "value": 3.4,
        "year": 2023
      },
      "AG.PRD.FOOD.XD": {
        "value": 109.39,
        "year": 2022
      }
    },
    "ARM": {
      "FP.CPI.TOTL.ZG": {
        "value": 0.27,
        "year": 2024
      },
      "NY.GDP.PCAP.CD": {
        "value": 8556.214,
        "year": 2024
      },
      "SN.ITK.DEFC.ZS": {
        "value": 2.5,
        "year": 2023
      },
      "AG.PRD.FOOD.XD": {
        "value": 83.87,
        "year": 2022
      }
    },
    "AUS": {
      "FP.CPI.TOTL.ZG": {
        "value": 3.167,
        "year": 2024
      },
      "NY.GDP.PCAP.CD": {
        "value": 64603.986,
        "year": 2024
      },
      "SN.ITK.DEFC.ZS": {
        "value": 2.5,
        "year": 2023
      },
      "AG.PRD.FOOD.XD": {
        "value": 112.1,
        "year": 2022
      }
    },
    "AUT": {
      "FP.CPI.TOTL.ZG": {
        "value": 2.938,
        "year": 2024
      },
      "NY.GDP.PCAP.CD": {
        "value": 58268.879,
        "year": 2024
      },
      "SN.ITK.DEFC.ZS": {
        "value": 2.5,
        "year": 2023
      },
      "AG.PRD.FOOD.XD": {
        "value": 100.45,
        "year": 2022
      }
    },
    "AZE": {
      "FP.CPI.TOTL.ZG": {
        "value": 2.212,
        "year": 2024
      },
      "NY.GDP.PCAP.CD": {
        "value": 7283.85,
        "year": 2024
      },
      "SN.ITK.DEFC.ZS": {
        "value": 2.5,
        "year": 2023
      },
      "AG.PRD.FOOD.XD": {
        "value": 129.02,
        "year": 2022
      }
    },
    "BHS": {
      "FP.CPI.TOTL.ZG": {
        "value": 0.409,
        "year": 2024
      },
      "NY.GDP.PCAP.CD": {
        "value": 39455.447,
        "year": 2024
      },
      "AG.PRD.FOOD.XD": {
        "value": 99.17,
        "year": 2022
      }
    },
    "BHR": {
      "FP.CPI.TOTL.ZG": {
        "value": 0.92,
        "year": 2024
      },
      "NY.GDP.PCAP.CD": {
        "value": 29653.568,
        "year": 2024
      },
      "AG.PRD.FOOD.XD": {
        "value": 129.17,
        "year": 2022
      }
    },
    "BGD": {
      "FP.CPI.TOTL.ZG": {
        "value": 10.466,
        "year": 2024
      },
      "NY.GDP.PCAP.CD": {
        "value": 2593.416,
        "year": 2024
      },
      "SN.ITK.DEFC.ZS": {
        "value": 10.4,
        "year": 2023
      },
      "AG.PRD.FOOD.XD": {
        "value": 125.2,
        "year": 2022
      }
    },
    "BRB": {
      "FP.CPI.TOTL.ZG": {
        "value": 1.446,
        "year": 2024
      },
      "NY.GDP.PCAP.CD": {
        "value": 26544.871,
        "year": 2024
      },
      "SN.ITK.DEFC.ZS": {
        "value": 4.4,
        "year": 2023
      },
      "AG.PRD.FOOD.XD": {
        "value": 102.71,
        "year": 2022
      }
    },
    "BLR": {
      "FP.CPI.TOTL.ZG": {
        "value": 5.785,
        "year": 2024
      },
      "NY.GDP.PCAP.CD": {
        "value": 8317.634,
        "year": 2024
      },
      "SN.ITK.DEFC.ZS": {
        "value": 2.5,
        "year": 2023
      },
      "AG.PRD.FOOD.XD": {
        "value": 102.53,
        "year": 2022
      }
    },
    "BEL": {
      "FP.CPI.TOTL.ZG": {
        "value": 3.143,
        "year": 2024
      },
      "NY.GDP.PCAP.CD": {
        "value": 56614.568,
        "year": 2024
      },
      "SN.ITK.DEFC.ZS": {
        "value": 2.5,
        "year": 2023
      },
      "AG.PRD.FOOD.XD": {
        "value": 100.0,
        "year": 2022
      }
    },
    "BLZ": {
      "FP.CPI.TOTL.ZG": {
        "value": 3.29,
        "year": 2024
      },
      "NY.GDP.PCAP.CD": {
        "value": 7681.244,
        "year": 2024
      },
      "SN.ITK.DEFC.ZS": {
        "value": 7.0,
        "year": 2023
      },
      "AG.PRD.FOOD.XD": {
        "value": 102.28,
        "year": 2022
      }
    },
    "BEN": {
      "FP.CPI.TOTL.ZG": {
        "value": 1.161,
        "year": 2024
      },
      "NY.GDP.PCAP.CD": {
        "value": 1485.38,
        "year": 2024
      },
      "SN.ITK.DEFC.ZS": {
        "value": 14.3,
        "year": 2023
      },
      "AG.PRD.FOOD.XD": {
        "value": 126.25,
        "year": 2022
      }
    },
    "BTN": {
      "FP.CPI.TOTL.ZG": {
        "value": 2.761,
        "year": 2024
      },
      "AG.PRD.FOOD.XD": {
        "value": 77.75,
        "year": 2022
      }
    },
    "BOL": {
      "FP.CPI.TOTL.ZG": {
        "value": 5.1,
        "year": 2024
      },
      "NY.GDP.PCAP.CD": {
        "value": 4421.166,
        "year": 2024
      },
      "SN.ITK.DEFC.ZS": {
        "value": 21.8,
        "year": 2023
      },
      "AG.PRD.FOOD.XD": {
        "value": 115.45,
        "year": 2022
      }
    },
    "BIH": {
      "FP.CPI.TOTL.ZG": {
        "value": 1.692,
        "year": 2024
      },
      "NY.GDP.PCAP.CD": {
        "value": 9358.788,
        "year": 2024
      },
      "SN.ITK.DEFC.ZS": {
        "value": 2.5,
        "year": 2023
      },
      "AG.PRD.FOOD.XD": {
        "value": 113.39,
        "year": 2022
      }
    },
    "BWA": {
      "FP.CPI.TOTL.ZG": {
        "value": 2.818,
        "year": 2024
      },
      "NY.GDP.PCAP.CD": {
        "value": 7695.753,
        "year": 2024
      },
      "SN.ITK.DEFC.ZS": {
        "value": 24.0,
        "year": 2023
      },
      "AG.PRD.FOOD.XD": {
        "value": 96.87,
        "year": 2022
      }
    },
    "BRA": {
      "FP.CPI.TOTL.ZG": {
        "value": 4.367,
        "year": 2024
      },
      "NY.GDP.PCAP.CD": {
        "value": 10310.549,
        "year": 2024
      },
      "SN.ITK.DEFC.ZS": {
        "value": 2.5,
        "year": 2023
      },
      "AG.PRD.FOOD.XD": {
        "value": 113.77,
        "year": 2022
      }
    },
    "BRN": {
      "FP.CPI.TOTL.ZG": {
        "value": -0.389,
        "year": 2024
      },
      "NY.GDP.PCAP.CD": {
        "value": 33153.474,
        "year": 2024
      },
      "AG.PRD.FOOD.XD": {
        "value": 119.3,
        "year": 2022
      }
    },
    "BGR": {
      "FP.CPI.TOTL.ZG": {
        "value": 2.447,
        "year": 2024
      },
      "NY.GDP.PCAP.CD": {
        "value": 17596.017,
        "year": 2024
      },
      "SN.ITK.DEFC.ZS": {
        "value": 2.5,
        "year": 2023
      },
      "AG.PRD.FOOD.XD": {
        "value": 100.74,
        "year": 2022
      }
    },
    "BFA": {
      "FP.CPI.TOTL.ZG": {
        "value": 4.191,
        "year": 2024
      },
      "NY.GDP.PCAP.CD": {
        "value": 981.993,
        "year": 2024
      },
      "SN.ITK.DEFC.ZS": {
        "value": 13.1,
        "year": 2023
      },
      "AG.PRD.FOOD.XD": {
        "value": 118.84,
        "year": 2022
      }
    },
    "BDI": {
      "FP.CPI.TOTL.ZG": {
        "value": 20.212,
        "year": 2024
      },
      "NY.GDP.PCAP.CD": {
        "value": 219.425,
        "year": 2024
      },
      "AG.PRD.FOOD.XD": {
        "value": 119.15,
        "year": 2022
      }
    },
    "CPV": {
      "FP.CPI.TOTL.ZG": {
        "value": 1.048,
        "year": 2024
      },
      "NY.GDP.PCAP.CD": {
        "value": 5192.482,
        "year": 2024
      },
      "SN.ITK.DEFC.ZS": {
        "value": 13.5,
        "year": 2023
      },
      "AG.PRD.FOOD.XD": {
        "value": 74.78,
        "year": 2022
      }
    },
    "KHM": {
      "FP.CPI.TOTL.ZG": {
        "value": 0.808,
        "year": 2024
      },
      "NY.GDP.PCAP.CD": {
        "value": 2627.88,
        "year": 2024
      },
      "SN.ITK.DEFC.ZS": {
        "value": 5.2,
        "year": 2023
      },
      "AG.PRD.FOOD.XD": {
        "value": 123.74,
        "year": 2022
      }
    },
    "CMR": {
      "FP.CPI.TOTL.ZG": {
        "value": 4.533,
        "year": 2024
      },
      "NY.GDP.PCAP.CD": {
        "value": 1830.008,
        "year": 2024
      },
      "SN.ITK.DEFC.ZS": {
        "value": 4.8,
        "year": 2023
      },
      "AG.PRD.FOOD.XD": {
        "value": 107.84,
        "year": 2022
      }
    },
    "CAN": {
      "FP.CPI.TOTL.ZG": {
        "value": 2.382,
        "year": 2024
      },
      "NY.GDP.PCAP.CD": {
        "value": 54340.348,
        "year": 2024
      },
      "SN.ITK.DEFC.ZS": {
        "value": 2.5,
        "year": 2023
      },
      "AG.PRD.FOOD.XD": {
        "value": 111.63,
        "year": 2022
      }
    },
    "CAF": {
      "FP.CPI.TOTL.ZG": {
        "value": 1.477,
        "year": 2024
      },
      "NY.GDP.PCAP.CD": {
        "value": 516.161,
        "year": 2024
      },
      "SN.ITK.DEFC.ZS": {
        "value": 29.8,
        "year": 2023
      },
      "AG.PRD.FOOD.XD": {
        "value": 147.99,
        "year": 2022
      }
    },
    "TCD": {
      "FP.CPI.TOTL.ZG": {
        "value": 8.9,
        "year": 2024
      },
      "NY.GDP.PCAP.CD": {
        "value": 961.56,
        "year": 2024
      },
      "SN.ITK.DEFC.ZS": {
        "value": 32.0,
        "year": 2023
      },
      "AG.PRD.FOOD.XD": {
        "value": 130.28,
        "year": 2022
      }
    },
    "CHL": {
      "FP.CPI.TOTL.ZG": {
        "value": 4.298,
        "year": 2024
      },
      "NY.GDP.PCAP.CD": {
        "value": 16709.889,
        "year": 2024
      },
      "SN.ITK.DEFC.ZS": {
        "value": 2.5,
        "year": 2023
      },
      "AG.PRD.FOOD.XD": {
        "value": 105.36,
        "year": 2022
      }
    },
    "CHN": {
      "FP.CPI.TOTL.ZG": {
        "value": 0.218,
        "year": 2024
      },
      "NY.GDP.PCAP.CD": {
        "value": 13303.148,
        "year": 2024
      },
      "SN.ITK.DEFC.ZS": {
        "value": 2.5,
        "year": 2023
      },
      "AG.PRD.FOOD.XD": {
        "value": 111.75,
        "year": 2022
      }
    },
    "COL": {
      "FP.CPI.TOTL.ZG": {
        "value": 6.609,
        "year": 2024
      },
      "NY.GDP.PCAP.CD": {
        "value": 7919.209,
        "year": 2024
      },
      "SN.ITK.DEFC.ZS": {
        "value": 3.9,
        "year": 2023
      },
      "AG.PRD.FOOD.XD": {
        "value": 110.64,
        "year": 2022
      }
    },
    "COM": {
      "FP.CPI.TOTL.ZG": {
        "value": 5.052,
        "year": 2024
      },
      "NY.GDP.PCAP.CD": {
        "value": 1662.757,
        "year": 2024
      },
      "SN.ITK.DEFC.ZS": {
        "value": 15.4,
        "year": 2023
      },
      "AG.PRD.FOOD.XD": {
        "value": 106.65,
        "year": 2022
      }
    },
    "COG": {
      "FP.CPI.TOTL.ZG": {
        "value": 3.091,
        "year": 2024
      },
      "NY.GDP.PCAP.CD": {
        "value": 2482.249,
        "year": 2024
      },
      "SN.ITK.DEFC.ZS": {
        "value": 26.4,
        "year": 2023
      },
      "AG.PRD.FOOD.XD": {
        "value": 106.13,
        "year": 2022
      }
    },
    "CRI": {
      "FP.CPI.TOTL.ZG": {
        "value": -0.413,
        "year": 2024
      },
      "NY.GDP.PCAP.CD": {
        "value": 18587.153,
        "year": 2024
      },
      "SN.ITK.DEFC.ZS": {
        "value": 2.5,
        "year": 2023
      },
      "AG.PRD.FOOD.XD": {
        "value": 100.36,
        "year": 2022
      },
      "SI.POV.NAHC": {
        "value": 17.1,
        "year": 2025
      }
    },
    "CIV": {
      "FP.CPI.TOTL.ZG": {
        "value": 3.451,
        "year": 2024
      },
      "NY.GDP.PCAP.CD": {
        "value": 2727.894,
        "year": 2024
      },
      "SN.ITK.DEFC.ZS": {
        "value": 11.1,
        "year": 2023
      },
      "AG.PRD.FOOD.XD": {
        "value": 121.86,
        "year": 2022
      }
    },
    "HRV": {
      "FP.CPI.TOTL.ZG": {
        "value": 2.972,
        "year": 2024
      },
      "NY.GDP.PCAP.CD": {
        "value": 24050.44,
        "year": 2024
      },
      "SN.ITK.DEFC.ZS": {
        "value": 2.5,
        "year": 2023
      },
      "AG.PRD.FOOD.XD": {
        "value": 89.5,
        "year": 2022
      }
    },
    "CYP": {
      "FP.CPI.TOTL.ZG": {
        "value": 1.8,
        "year": 2024
      },
      "NY.GDP.PCAP.CD": {
        "value": 38674.293,
        "year": 2024
      },
      "SN.ITK.DEFC.ZS": {
        "value": 2.5,
        "year": 2023
      },
      "AG.PRD.FOOD.XD": {
        "value": 108.71,
        "year": 2022
      }
    },
    "CZE": {
      "FP.CPI.TOTL.ZG": {
        "value": 2.435,
        "year": 2024
      },
      "NY.GDP.PCAP.CD": {
        "value": 31823.308,
        "year": 2024
      },
      "SN.ITK.DEFC.ZS": {
        "value": 2.5,
        "year": 2023
      },
      "AG.PRD.FOOD.XD": {
        "value": 97.66,
        "year": 2022
      }
    },
    "DNK": {
      "FP.CPI.TOTL.ZG": {
        "value": 1.372,
        "year": 2024
      },
      "NY.GDP.PCAP.CD": {
        "value": 71026.483,
        "year": 2024
      },
      "SN.ITK.DEFC.ZS": {
        "value": 2.5,
        "year": 2023
      },
      "AG.PRD.FOOD.XD": {
        "value": 103.83,
        "year": 2022
      }
    },
    "DJI": {
      "FP.CPI.TOTL.ZG": {
        "value": 2.112,
        "year": 2024
      },
      "NY.GDP.PCAP.CD": {
        "value": 3552.723,
        "year": 2024
      },
      "SN.ITK.DEFC.ZS": {
        "value": 12.9,
        "year": 2023
      },
      "AG.PRD.FOOD.XD": {
        "value": 133.0,
        "year": 2022
      }
    },
    "DMA": {
      "FP.CPI.TOTL.ZG": {
        "value": 2.569,
        "year": 2024
      },
      "NY.GDP.PCAP.CD": {
        "value": 10405.279,
        "year": 2024
      },
      "SN.ITK.DEFC.ZS": {
        "value": 3.6,
        "year": 2023
      },
      "AG.PRD.FOOD.XD": {
        "value": 100.85,
        "year": 2022
      }
    },
    "DOM": {
      "FP.CPI.TOTL.ZG": {
        "value": 3.302,
        "year": 2024
      },
      "NY.GDP.PCAP.CD": {
        "value": 10875.662,
        "year": 2024
      },
      "SN.ITK.DEFC.ZS": {
        "value": 3.6,
        "year": 2023
      },
      "AG.PRD.FOOD.XD": {
        "value": 127.89,
        "year": 2022
      },
      "SI.POV.NAHC": {
        "value": 17.3,
        "year": 2025
      }
    },
    "ECU": {
      "FP.CPI.TOTL.ZG": {
        "value": 1.547,
        "year": 2024
      },
      "NY.GDP.PCAP.CD": {
        "value": 6874.706,
        "year": 2024
      },
      "SN.ITK.DEFC.ZS": {
        "value": 12.1,
        "year": 2023
      },
      "AG.PRD.FOOD.XD": {
        "value": 98.86,
        "year": 2022
      },
      "SI.POV.NAHC": {
        "value": 21.4,
        "year": 2025
      }
    },
    "EGY": {
      "FP.CPI.TOTL.ZG": {
        "value": 28.271,
        "year": 2024
      },
      "NY.GDP.PCAP.CD": {
        "value": 3338.474,
        "year": 2024
      },
      "SN.ITK.DEFC.ZS": {
        "value": 9.4,
        "year": 2023
      },
      "AG.PRD.FOOD.XD": {
        "value": 109.07,
        "year": 2022
      }
    },
    "SLV": {
      "FP.CPI.TOTL.ZG": {
        "value": 0.854,
        "year": 2024
      },
      "NY.GDP.PCAP.CD": {
        "value": 5579.66,
        "year": 2024
      },
      "SN.ITK.DEFC.ZS": {
        "value": 6.7,
        "year": 2023
      },
      "AG.PRD.FOOD.XD": {
        "value": 102.68,
        "year": 2022
      }
    },
    "GNQ": {
      "FP.CPI.TOTL.ZG": {
        "value": 2.921,
        "year": 2024
      },
      "NY.GDP.PCAP.CD": {
        "value": 6745.4,
        "year": 2024
      },
      "AG.PRD.FOOD.XD": {
        "value": 103.43,
        "year": 2022
      }
    },
    "EST": {
      "FP.CPI.TOTL.ZG": {
        "value": 3.519,
        "year": 2024
      },
      "NY.GDP.PCAP.CD": {
        "value": 31428.355,
        "year": 2024
      },
      "SN.ITK.DEFC.ZS": {
        "value": 2.5,
        "year": 2023
      },
      "AG.PRD.FOOD.XD": {
        "value": 105.65,
        "year": 2022
      }
    },
    "ETH": {
      "FP.CPI.TOTL.ZG": {
        "value": 21.038,
        "year": 2024
      },
      "NY.GDP.PCAP.CD": {
        "value": 1133.883,
        "year": 2024
      },
      "SN.ITK.DEFC.ZS": {
        "value": 19.7,
        "year": 2023
      },
      "AG.PRD.FOOD.XD": {
        "value": 116.31,
        "year": 2022
      }
    },
    "FJI": {
      "FP.CPI.TOTL.ZG": {
        "value": 3.891,
        "year": 2024
      },
      "NY.GDP.PCAP.CD": {
        "value": 6425.742,
        "year": 2024
      },
      "SN.ITK.DEFC.ZS": {
        "value": 6.8,
        "year": 2023
      },
      "AG.PRD.FOOD.XD": {
        "value": 139.65,
        "year": 2022
      }
    },
    "FIN": {
      "FP.CPI.TOTL.ZG": {
        "value": 1.566,
        "year": 2024
      },
      "NY.GDP.PCAP.CD": {
        "value": 53149.767,
        "year": 2024
      },
      "SN.ITK.DEFC.ZS": {
        "value": 2.5,
        "year": 2023
      },
      "AG.PRD.FOOD.XD": {
        "value": 98.15,
        "year": 2022
      }
    },
    "FRA": {
      "FP.CPI.TOTL.ZG": {
        "value": 1.999,
        "year": 2024
      },
      "NY.GDP.PCAP.CD": {
        "value": 46103.084,
        "year": 2024
      },
      "SN.ITK.DEFC.ZS": {
        "value": 2.5,
        "year": 2023
      },
      "AG.PRD.FOOD.XD": {
        "value": 94.02,
        "year": 2022
      }
    },
    "GAB": {
      "FP.CPI.TOTL.ZG": {
        "value": 1.173,
        "year": 2024
      },
      "NY.GDP.PCAP.CD": {
        "value": 8230.043,
        "year": 2024
      },
      "SN.ITK.DEFC.ZS": {
        "value": 25.3,
        "year": 2023
      },
      "AG.PRD.FOOD.XD": {
        "value": 105.76,
        "year": 2022
      }
    },
    "GMB": {
      "FP.CPI.TOTL.ZG": {
        "value": 11.561,
        "year": 2024
      },
      "NY.GDP.PCAP.CD": {
        "value": 871.34,
        "year": 2024
      },
      "SN.ITK.DEFC.ZS": {
        "value": 16.8,
        "year": 2023
      },
      "AG.PRD.FOOD.XD": {
        "value": 71.08,
        "year": 2022
      }
    },
    "GEO": {
      "FP.CPI.TOTL.ZG": {
        "value": 1.11,
        "year": 2024
      },
      "NY.GDP.PCAP.CD": {
        "value": 9241.491,
        "year": 2024
      },
      "SN.ITK.DEFC.ZS": {
        "value": 2.5,
        "year": 2023
      },
      "AG.PRD.FOOD.XD": {
        "value": 113.64,
        "year": 2022
      }
    },
    "DEU": {
      "FP.CPI.TOTL.ZG": {
        "value": 2.256,
        "year": 2024
      },
      "NY.GDP.PCAP.CD": {
        "value": 56103.732,
        "year": 2024
      },
      "SN.ITK.DEFC.ZS": {
        "value": 2.5,
        "year": 2023
      },
      "AG.PRD.FOOD.XD": {
        "value": 92.71,
        "year": 2022
      }
    },
    "GHA": {
      "FP.CPI.TOTL.ZG": {
        "value": 22.848,
        "year": 2024
      },
      "NY.GDP.PCAP.CD": {
        "value": 2390.772,
        "year": 2024
      },
      "SN.ITK.DEFC.ZS": {
        "value": 6.3,
        "year": 2023
      },
      "AG.PRD.FOOD.XD": {
        "value": 135.5,
        "year": 2022
      }
    },
    "GRC": {
      "FP.CPI.TOTL.ZG": {
        "value": 2.741,
        "year": 2024
      },
      "NY.GDP.PCAP.CD": {
        "value": 24626.148,
        "year": 2024
      },
      "SN.ITK.DEFC.ZS": {
        "value": 2.5,
        "year": 2023
      },
      "AG.PRD.FOOD.XD": {
        "value": 102.76,
        "year": 2022
      }
    },
    "GRD": {
      "FP.CPI.TOTL.ZG": {
        "value": 1.086,
        "year": 2024
      },
      "NY.GDP.PCAP.CD": {
        "value": 11705.09,
        "year": 2024
      },
      "AG.PRD.FOOD.XD": {
        "value": 86.71,
        "year": 2022
      }
    },
    "GTM": {
      "FP.CPI.TOTL.ZG": {
        "value": 2.87,
        "year": 2024
      },
      "NY.GDP.PCAP.CD": {
        "value": 6150.026,
        "year": 2024
      },
      "SN.ITK.DEFC.ZS": {
        "value": 11.8,
        "year": 2023
      },
      "AG.PRD.FOOD.XD": {
        "value": 107.89,
        "year": 2022
      }
    },
    "GIN": {
      "FP.CPI.TOTL.ZG": {
        "value": 8.123,
        "year": 2024
      },
      "NY.GDP.PCAP.CD": {
        "value": 1694.954,
        "year": 2024
      },
      "SN.ITK.DEFC.ZS": {
        "value": 11.4,
        "year": 2023
      },
      "AG.PRD.FOOD.XD": {
        "value": 144.8,
        "year": 2022
      }
    },
    "GNB": {
      "FP.CPI.TOTL.ZG": {
        "value": 3.766,
        "year": 2024
      },
      "NY.GDP.PCAP.CD": {
        "value": 1007.742,
        "year": 2024
      },
      "SN.ITK.DEFC.ZS": {
        "value": 22.1,
        "year": 2023
      },
      "AG.PRD.FOOD.XD": {
        "value": 122.25,
        "year": 2022
      }
    },
    "GUY": {
      "FP.CPI.TOTL.ZG": {
        "value": 2.904,
        "year": 2024
      },
      "NY.GDP.PCAP.CD": {
        "value": 29675.244,
        "year": 2024
      },
      "SN.ITK.DEFC.ZS": {
        "value": 2.5,
        "year": 2023
      },
      "AG.PRD.FOOD.XD": {
        "value": 111.69,
        "year": 2022
      }
    },
    "HTI": {
      "FP.CPI.TOTL.ZG": {
        "value": 26.949,
        "year": 2024
      },
      "NY.GDP.PCAP.CD": {
        "value": 2142.623,
        "year": 2024
      },
      "SN.ITK.DEFC.ZS": {
        "value": 54.2,
        "year": 2023
      },
      "AG.PRD.FOOD.XD": {
        "value": 77.85,
        "year": 2022
      }
    },
    "HND": {
      "FP.CPI.TOTL.ZG": {
        "value": 4.606,
        "year": 2024
      },
      "NY.GDP.PCAP.CD": {
        "value": 3426.435,
        "year": 2024
      },
      "SN.ITK.DEFC.ZS": {
        "value": 14.8,
        "year": 2023
      },
      "AG.PRD.FOOD.XD": {
        "value": 107.0,
        "year": 2022
      },
      "SI.POV.NAHC": {
        "value": 60.1,
        "year": 2025
      }
    },
    "HKG": {
      "FP.CPI.TOTL.ZG": {
        "value": 1.73,
        "year": 2024
      },
      "NY.GDP.PCAP.CD": {
        "value": 54074.693,
        "year": 2024
      },
      "SN.ITK.DEFC.ZS": {
        "value": 3.1,
        "year": 2023
      },
      "AG.PRD.FOOD.XD": {
        "value": 141.66,
        "year": 2022
      }
    },
    "HUN": {
      "FP.CPI.TOTL.ZG": {
        "value": 3.704,
        "year": 2024
      },
      "NY.GDP.PCAP.CD": {
        "value": 23292.326,
        "year": 2024
      },
      "SN.ITK.DEFC.ZS": {
        "value": 2.5,
        "year": 2023
      },
      "AG.PRD.FOOD.XD": {
        "value": 74.66,
        "year": 2022
      }
    },
    "ISL": {
      "FP.CPI.TOTL.ZG": {
        "value": 5.857,
        "year": 2024
      },
      "NY.GDP.PCAP.CD": {
        "value": 86040.531,
        "year": 2024
      },
      "SN.ITK.DEFC.ZS": {
        "value": 2.5,
        "year": 2023
      },
      "AG.PRD.FOOD.XD": {
        "value": 102.07,
        "year": 2022
      }
    },
    "IND": {
      "FP.CPI.TOTL.ZG": {
        "value": 4.953,
        "year": 2024
      },
      "NY.GDP.PCAP.CD": {
        "value": 2694.738,
        "year": 2024
      },
      "SN.ITK.DEFC.ZS": {
        "value": 12.0,
        "year": 2023
      },
      "AG.PRD.FOOD.XD": {
        "value": 127.82,
        "year": 2022
      }
    },
    "IDN": {
      "FP.CPI.TOTL.ZG": {
        "value": 2.182,
        "year": 2024
      },
      "NY.GDP.PCAP.CD": {
        "value": 4925.43,
        "year": 2024
      },
      "SN.ITK.DEFC.ZS": {
        "value": 6.3,
        "year": 2023
      },
      "AG.PRD.FOOD.XD": {
        "value": 117.14,
        "year": 2022
      }
    },
    "IRN": {
      "FP.CPI.TOTL.ZG": {
        "value": 32.456,
        "year": 2024
      },
      "NY.GDP.PCAP.CD": {
        "value": 5190.17,
        "year": 2024
      },
      "SN.ITK.DEFC.ZS": {
        "value": 6.8,
        "year": 2023
      },
      "AG.PRD.FOOD.XD": {
        "value": 83.89,
        "year": 2022
      }
    },
    "IRQ": {
      "FP.CPI.TOTL.ZG": {
        "value": -12.297,
        "year": 2024
      },
      "NY.GDP.PCAP.CD": {
        "value": 6073.61,
        "year": 2024
      },
      "SN.ITK.DEFC.ZS": {
        "value": 14.9,
        "year": 2023
      },
      "AG.PRD.FOOD.XD": {
        "value": 106.36,
        "year": 2022
      }
    },
    "IRL": {
      "FP.CPI.TOTL.ZG": {
        "value": 2.113,
        "year": 2024
      },
      "NY.GDP.PCAP.CD": {
        "value": 112894.953,
        "year": 2024
      },
      "SN.ITK.DEFC.ZS": {
        "value": 2.5,
        "year": 2023
      },
      "AG.PRD.FOOD.XD": {
        "value": 121.51,
        "year": 2022
      }
    },
    "ISR": {
      "FP.CPI.TOTL.ZG": {
        "value": 3.075,
        "year": 2024
      },
      "NY.GDP.PCAP.CD": {
        "value": 54176.684,
        "year": 2024
      },
      "SN.ITK.DEFC.ZS": {
        "value": 2.5,
        "year": 2023
      },
      "AG.PRD.FOOD.XD": {
        "value": 105.48,
        "year": 2022
      }
    },
    "ITA": {
      "FP.CPI.TOTL.ZG": {
        "value": 0.982,
        "year": 2024
      },
      "NY.GDP.PCAP.CD": {
        "value": 40385.341,
        "year": 2024
      },
      "SN.ITK.DEFC.ZS": {
        "value": 2.5,
        "year": 2023
      },
      "AG.PRD.FOOD.XD": {
        "value": 96.97,
        "year": 2022
      }
    },
    "JAM": {
      "FP.CPI.TOTL.ZG": {
        "value": 5.412,
        "year": 2024
      },
      "NY.GDP.PCAP.CD": {
        "value": 7753.801,
        "year": 2024
      },
      "SN.ITK.DEFC.ZS": {
        "value": 7.7,
        "year": 2023
      },
      "AG.PRD.FOOD.XD": {
        "value": 113.26,
        "year": 2022
      }
    },
    "JPN": {
      "FP.CPI.TOTL.ZG": {
        "value": 2.739,
        "year": 2024
      },
      "NY.GDP.PCAP.CD": {
        "value": 32487.078,
        "year": 2024
      },
      "AG.PRD.FOOD.XD": {
        "value": 100.27,
        "year": 2022
      }
    },
    "JOR": {
      "FP.CPI.TOTL.ZG": {
        "value": 1.557,
        "year": 2024
      },
      "NY.GDP.PCAP.CD": {
        "value": 4618.096,
        "year": 2024
      },
      "SN.ITK.DEFC.ZS": {
        "value": 14.3,
        "year": 2023
      },
      "AG.PRD.FOOD.XD": {
        "value": 110.25,
        "year": 2022
      }
    },
    "KAZ": {
      "FP.CPI.TOTL.ZG": {
        "value": 8.691,
        "year": 2024
      },
      "NY.GDP.PCAP.CD": {
        "value": 14154.632,
        "year": 2024
      },
      "SN.ITK.DEFC.ZS": {
        "value": 2.5,
        "year": 2023
      },
      "AG.PRD.FOOD.XD": {
        "value": 127.76,
        "year": 2022
      }
    },
    "KEN": {
      "FP.CPI.TOTL.ZG": {
        "value": 4.49,
        "year": 2024
      },
      "NY.GDP.PCAP.CD": {
        "value": 2132.435,
        "year": 2024
      },
      "SN.ITK.DEFC.ZS": {
        "value": 36.8,
        "year": 2023
      },
      "AG.PRD.FOOD.XD": {
        "value": 112.38,
        "year": 2022
      }
    },
    "KIR": {
      "FP.CPI.TOTL.ZG": {
        "value": 2.455,
        "year": 2024
      },
      "NY.GDP.PCAP.CD": {
        "value": 2288.635,
        "year": 2024
      },
      "SN.ITK.DEFC.ZS": {
        "value": 4.1,
        "year": 2023
      },
      "AG.PRD.FOOD.XD": {
        "value": 97.32,
        "year": 2022
      }
    },
    "KOR": {
      "FP.CPI.TOTL.ZG": {
        "value": 2.322,
        "year": 2024
      },
      "NY.GDP.PCAP.CD": {
        "value": 36238.64,
        "year": 2024
      },
      "SN.ITK.DEFC.ZS": {
        "value": 2.5,
        "year": 2023
      },
      "AG.PRD.FOOD.XD": {
        "value": 101.21,
        "year": 2022
      }
    },
    "XKX": {
      "FP.CPI.TOTL.ZG": {
        "value": 1.619,
        "year": 2024
      },
      "NY.GDP.PCAP.CD": {
        "value": 7023.066,
        "year": 2024
      }
    },
    "KWT": {
      "FP.CPI.TOTL.ZG": {
        "value": 2.899,
        "year": 2024
      },
      "NY.GDP.PCAP.CD": {
        "value": 32717.719,
        "year": 2024
      },
      "SN.ITK.DEFC.ZS": {
        "value": 2.5,
        "year": 2023
      },
      "AG.PRD.FOOD.XD": {
        "value": 130.87,
        "year": 2022
      }
    },
    "KGZ": {
      "FP.CPI.TOTL.ZG": {
        "value": 4.998,
        "year": 2024
      },
      "NY.GDP.PCAP.CD": {
        "value": 2420.185,
        "year": 2024
      },
      "SN.ITK.DEFC.ZS": {
        "value": 5.1,
        "year": 2023
      },
      "AG.PRD.FOOD.XD": {
        "value": 112.75,
        "year": 2022
      }
    },
    "LAO": {
      "FP.CPI.TOTL.ZG": {
        "value": 23.131,
        "year": 2024
      },
      "NY.GDP.PCAP.CD": {
        "value": 2123.979,
        "year": 2024
      },
      "AG.PRD.FOOD.XD": {
        "value": 114.84,
        "year": 2022
      }
    },
    "LVA": {
      "FP.CPI.TOTL.ZG": {
        "value": 1.266,
        "year": 2024
      },
      "NY.GDP.PCAP.CD": {
        "value": 23409.085,
        "year": 2024
      },
      "SN.ITK.DEFC.ZS": {
        "value": 2.5,
        "year": 2023
      },
      "AG.PRD.FOOD.XD": {
        "value": 103.93,
        "year": 2022
      }
    },
    "LBN": {
      "FP.CPI.TOTL.ZG": {
        "value": 45.243,
        "year": 2024
      },
      "SN.ITK.DEFC.ZS": {
        "value": 8.7,
        "year": 2023
      },
      "AG.PRD.FOOD.XD": {
        "value": 104.14,
        "year": 2022
      }
    },
    "LSO": {
      "FP.CPI.TOTL.ZG": {
        "value": 6.105,
        "year": 2024
      },
      "NY.GDP.PCAP.CD": {
        "value": 971.908,
        "year": 2024
      },
      "AG.PRD.FOOD.XD": {
        "value": 98.67,
        "year": 2022
      }
    },
    "LBR": {
      "FP.CPI.TOTL.ZG": {
        "value": 8.215,
        "year": 2024
      },
      "NY.GDP.PCAP.CD": {
        "value": 851.498,
        "year": 2024
      },
      "SN.ITK.DEFC.ZS": {
        "value": 35.5,
        "year": 2023
      },
      "AG.PRD.FOOD.XD": {
        "value": 102.67,
        "year": 2022
      }
    },
    "LBY": {
      "FP.CPI.TOTL.ZG": {
        "value": 2.126,
        "year": 2024
      },
      "NY.GDP.PCAP.CD": {
        "value": 6569.164,
        "year": 2024
      },
      "SN.ITK.DEFC.ZS": {
        "value": 16.5,
        "year": 2023
      },
      "AG.PRD.FOOD.XD": {
        "value": 105.75,
        "year": 2022
      }
    },
    "LTU": {
      "FP.CPI.TOTL.ZG": {
        "value": 0.716,
        "year": 2024
      },
      "NY.GDP.PCAP.CD": {
        "value": 29384.019,
        "year": 2024
      },
      "SN.ITK.DEFC.ZS": {
        "value": 2.5,
        "year": 2023
      },
      "AG.PRD.FOOD.XD": {
        "value": 99.53,
        "year": 2022
      }
    },
    "LUX": {
      "FP.CPI.TOTL.ZG": {
        "value": 2.051,
        "year": 2024
      },
      "NY.GDP.PCAP.CD": {
        "value": 137781.682,
        "year": 2024
      },
      "SN.ITK.DEFC.ZS": {
        "value": 2.5,
        "year": 2023
      },
      "AG.PRD.FOOD.XD": {
        "value": 114.89,
        "year": 2022
      }
    },
    "MAC": {
      "FP.CPI.TOTL.ZG": {
        "value": 0.672,
        "year": 2024
      },
      "NY.GDP.PCAP.CD": {
        "value": 72004.744,
        "year": 2024
      },
      "SN.ITK.DEFC.ZS": {
        "value": 11.2,
        "year": 2023
      },
      "AG.PRD.FOOD.XD": {
        "value": 81.34,
        "year": 2022
      }
    },
    "MDG": {
      "FP.CPI.TOTL.ZG": {
        "value": 7.613,
        "year": 2024
      },
      "NY.GDP.PCAP.CD": {
        "value": 544.988,
        "year": 2024
      },
      "SN.ITK.DEFC.ZS": {
        "value": 39.5,
        "year": 2023
      },
      "AG.PRD.FOOD.XD": {
        "value": 105.91,
        "year": 2022
      }
    },
    "MWI": {
      "FP.CPI.TOTL.ZG": {
        "value": 32.18,
        "year": 2024
      },
      "NY.GDP.PCAP.CD": {
        "value": 522.57,
        "year": 2024
      },
      "SN.ITK.DEFC.ZS": {
        "value": 21.4,
        "year": 2023
      },
      "AG.PRD.FOOD.XD": {
        "value": 146.13,
        "year": 2022
      }
    },
    "MYS": {
      "FP.CPI.TOTL.ZG": {
        "value": 1.834,
        "year": 2024
      },
      "NY.GDP.PCAP.CD": {
        "value": 11874.427,
        "year": 2024
      },
      "SN.ITK.DEFC.ZS": {
        "value": 2.5,
        "year": 2023
      },
      "AG.PRD.FOOD.XD": {
        "value": 102.8,
        "year": 2022
      }
    },
    "MDV": {
      "FP.CPI.TOTL.ZG": {
        "value": 1.4,
        "year": 2024
      },
      "NY.GDP.PCAP.CD": {
        "value": 13379.351,
        "year": 2024
      },
      "AG.PRD.FOOD.XD": {
        "value": 94.49,
        "year": 2022
      }
    },
    "MLI": {
      "FP.CPI.TOTL.ZG": {
        "value": 3.206,
        "year": 2024
      },
      "NY.GDP.PCAP.CD": {
        "value": 1094.619,
        "year": 2024
      },
      "SN.ITK.DEFC.ZS": {
        "value": 12.3,
        "year": 2023
      },
      "AG.PRD.FOOD.XD": {
        "value": 136.03,
        "year": 2022
      }
    },
    "MLT": {
      "FP.CPI.TOTL.ZG": {
        "value": 1.651,
        "year": 2024
      },
      "NY.GDP.PCAP.CD": {
        "value": 43898.578,
        "year": 2024
      },
      "SN.ITK.DEFC.ZS": {
        "value": 2.5,
        "year": 2023
      },
      "AG.PRD.FOOD.XD": {
        "value": 75.95,
        "year": 2022
      }
    },
    "MRT": {
      "FP.CPI.TOTL.ZG": {
        "value": 2.492,
        "year": 2024
      },
      "NY.GDP.PCAP.CD": {
        "value": 2110.12,
        "year": 2024
      },
      "SN.ITK.DEFC.ZS": {
        "value": 8.7,
        "year": 2023
      },
      "AG.PRD.FOOD.XD": {
        "value": 116.51,
        "year": 2022
      }
    },
    "MUS": {
      "FP.CPI.TOTL.ZG": {
        "value": 3.605,
        "year": 2024
      },
      "NY.GDP.PCAP.CD": {
        "value": 11990.78,
        "year": 2024
      },
      "SN.ITK.DEFC.ZS": {
        "value": 8.7,
        "year": 2023
      },
      "AG.PRD.FOOD.XD": {
        "value": 84.4,
        "year": 2022
      }
    },
    "MEX": {
      "FP.CPI.TOTL.ZG": {
        "value": 4.722,
        "year": 2024
      },
      "NY.GDP.PCAP.CD": {
        "value": 14185.781,
        "year": 2024
      },
      "SN.ITK.DEFC.ZS": {
        "value": 2.7,
        "year": 2023
      },
      "AG.PRD.FOOD.XD": {
        "value": 117.03,
        "year": 2022
      }
    },
    "MDA": {
      "FP.CPI.TOTL.ZG": {
        "value": 4.678,
        "year": 2024
      },
      "NY.GDP.PCAP.CD": {
        "value": 7576.196,
        "year": 2024
      },
      "SN.ITK.DEFC.ZS": {
        "value": 2.5,
        "year": 2023
      },
      "AG.PRD.FOOD.XD": {
        "value": 89.67,
        "year": 2022
      }
    },
    "MNG": {
      "FP.CPI.TOTL.ZG": {
        "value": 6.198,
        "year": 2024
      },
      "NY.GDP.PCAP.CD": {
        "value": 6750.63,
        "year": 2024
      },
      "SN.ITK.DEFC.ZS": {
        "value": 2.5,
        "year": 2023
      },
      "AG.PRD.FOOD.XD": {
        "value": 157.87,
        "year": 2022
      }
    },
    "MNE": {
      "FP.CPI.TOTL.ZG": {
        "value": 3.337,
        "year": 2024
      },
      "NY.GDP.PCAP.CD": {
        "value": 13263.328,
        "year": 2024
      },
      "SN.ITK.DEFC.ZS": {
        "value": 2.5,
        "year": 2023
      },
      "AG.PRD.FOOD.XD": {
        "value": 100.56,
        "year": 2022
      }
    },
    "MAR": {
      "FP.CPI.TOTL.ZG": {
        "value": 0.985,
        "year": 2024
      },
      "NY.GDP.PCAP.CD": {
        "value": 4153.194,
        "year": 2024
      },
      "SN.ITK.DEFC.ZS": {
        "value": 7.0,
        "year": 2023
      },
      "AG.PRD.FOOD.XD": {
        "value": 106.07,
        "year": 2022
      }
    },
    "MOZ": {
      "FP.CPI.TOTL.ZG": {
        "value": 4.079,
        "year": 2024
      },
      "NY.GDP.PCAP.CD": {
        "value": 656.777,
        "year": 2024
      },
      "SN.ITK.DEFC.ZS": {
        "value": 21.8,
        "year": 2023
      },
      "AG.PRD.FOOD.XD": {
        "value": 161.67,
        "year": 2022
      }
    },
    "NAM": {
      "FP.CPI.TOTL.ZG": {
        "value": 4.239,
        "year": 2024
      },
      "NY.GDP.PCAP.CD": {
        "value": 4413.128,
        "year": 2024
      },
      "SN.ITK.DEFC.ZS": {
        "value": 18.1,
        "year": 2023
      },
      "AG.PRD.FOOD.XD": {
        "value": 100.53,
        "year": 2022
      }
    },
    "NPL": {
      "FP.CPI.TOTL.ZG": {
        "value": 4.685,
        "year": 2024
      },
      "NY.GDP.PCAP.CD": {
        "value": 1447.31,
        "year": 2024
      },
      "SN.ITK.DEFC.ZS": {
        "value": 5.3,
        "year": 2023
      },
      "AG.PRD.FOOD.XD": {
        "value": 123.18,
        "year": 2022
      }
    },
    "NLD": {
      "FP.CPI.TOTL.ZG": {
        "value": 3.348,
        "year": 2024
      },
      "NY.GDP.PCAP.CD": {
        "value": 67520.422,
        "year": 2024
      },
      "SN.ITK.DEFC.ZS": {
        "value": 2.5,
        "year": 2023
      },
      "AG.PRD.FOOD.XD": {
        "value": 101.0,
        "year": 2022
      }
    },
    "NZL": {
      "FP.CPI.TOTL.ZG": {
        "value": 2.923,
        "year": 2024
      },
      "NY.GDP.PCAP.CD": {
        "value": 49205.179,
        "year": 2024
      },
      "SN.ITK.DEFC.ZS": {
        "value": 2.5,
        "year": 2023
      },
      "AG.PRD.FOOD.XD": {
        "value": 100.57,
        "year": 2022
      }
    },
    "NIC": {
      "FP.CPI.TOTL.ZG": {
        "value": 4.625,
        "year": 2024
      },
      "NY.GDP.PCAP.CD": {
        "value": 2847.54,
        "year": 2024
      },
      "AG.PRD.FOOD.XD": {
        "value": 127.92,
        "year": 2022
      }
    },
    "NER": {
      "FP.CPI.TOTL.ZG": {
        "value": 9.072,
        "year": 2024
      },
      "NY.GDP.PCAP.CD": {
        "value": 735.27,
        "year": 2024
      },
      "SN.ITK.DEFC.ZS": {
        "value": 12.9,
        "year": 2023
      },
      "AG.PRD.FOOD.XD": {
        "value": 132.61,
        "year": 2022
      }
    },
    "NGA": {
      "FP.CPI.TOTL.ZG": {
        "value": 33.242,
        "year": 2024
      },
      "NY.GDP.PCAP.CD": {
        "value": 1084.16,
        "year": 2024
      },
      "SN.ITK.DEFC.ZS": {
        "value": 19.9,
        "year": 2023
      },
      "AG.PRD.FOOD.XD": {
        "value": 119.85,
        "year": 2022
      }
    },
    "MKD": {
      "FP.CPI.TOTL.ZG": {
        "value": 3.49,
        "year": 2024
      },
      "NY.GDP.PCAP.CD": {
        "value": 9291.857,
        "year": 2024
      },
      "SN.ITK.DEFC.ZS": {
        "value": 2.5,
        "year": 2023
      },
      "AG.PRD.FOOD.XD": {
        "value": 100.68,
        "year": 2022
      }
    },
    "NOR": {
      "FP.CPI.TOTL.ZG": {
        "value": 3.145,
        "year": 2024
      },
      "NY.GDP.PCAP.CD": {
        "value": 86785.433,
        "year": 2024
      },
      "SN.ITK.DEFC.ZS": {
        "value": 2.5,
        "year": 2023
      },
      "AG.PRD.FOOD.XD": {
        "value": 102.72,
        "year": 2022
      }
    },
    "OMN": {
      "FP.CPI.TOTL.ZG": {
        "value": 0.594,
        "year": 2024
      },
      "NY.GDP.PCAP.CD": {
        "value": 20285.227,
        "year": 2024
      },
      "SN.ITK.DEFC.ZS": {
        "value": 5.9,
        "year": 2023
      },
      "AG.PRD.FOOD.XD": {
        "value": 170.06,
        "year": 2022
      }
    },
    "PAK": {
      "FP.CPI.TOTL.ZG": {
        "value": 12.633,
        "year": 2024
      },
      "NY.GDP.PCAP.CD": {
        "value": 1478.773,
        "year": 2024
      },
      "SN.ITK.DEFC.ZS": {
        "value": 16.5,
        "year": 2023
      },
      "AG.PRD.FOOD.XD": {
        "value": 122.43,
        "year": 2022
      }
    },
    "PLW": {
      "FP.CPI.TOTL.ZG": {
        "value": 2.232,
        "year": 2024
      }
    },
    "PAN": {
      "FP.CPI.TOTL.ZG": {
        "value": 0.693,
        "year": 2024
      },
      "NY.GDP.PCAP.CD": {
        "value": 19161.219,
        "year": 2024
      },
      "SN.ITK.DEFC.ZS": {
        "value": 5.7,
        "year": 2023
      },
      "AG.PRD.FOOD.XD": {
        "value": 115.45,
        "year": 2022
      }
    },
    "PNG": {
      "FP.CPI.TOTL.ZG": {
        "value": 0.602,
        "year": 2024
      },
      "NY.GDP.PCAP.CD": {
        "value": 3006.706,
        "year": 2024
      },
      "SN.ITK.DEFC.ZS": {
        "value": 28.7,
        "year": 2023
      },
      "AG.PRD.FOOD.XD": {
        "value": 100.55,
        "year": 2022
      }
    },
    "PRY": {
      "FP.CPI.TOTL.ZG": {
        "value": 3.835,
        "year": 2024
      },
      "NY.GDP.PCAP.CD": {
        "value": 6416.097,
        "year": 2024
      },
      "SN.ITK.DEFC.ZS": {
        "value": 5.2,
        "year": 2023
      },
      "AG.PRD.FOOD.XD": {
        "value": 85.44,
        "year": 2022
      }
    },
    "PER": {
      "FP.CPI.TOTL.ZG": {
        "value": 2.008,
        "year": 2024
      },
      "NY.GDP.PCAP.CD": {
        "value": 8452.372,
        "year": 2024
      },
      "SN.ITK.DEFC.ZS": {
        "value": 6.9,
        "year": 2023
      },
      "AG.PRD.FOOD.XD": {
        "value": 128.07,
        "year": 2022
      }
    },
    "PHL": {
      "FP.CPI.TOTL.ZG": {
        "value": 3.213,
        "year": 2024
      },
      "NY.GDP.PCAP.CD": {
        "value": 3984.832,
        "year": 2024
      },
      "SN.ITK.DEFC.ZS": {
        "value": 3.0,
        "year": 2023
      },
      "AG.PRD.FOOD.XD": {
        "value": 100.51,
        "year": 2022
      }
    },
    "POL": {
      "FP.CPI.TOTL.ZG": {
        "value": 3.791,
        "year": 2024
      },
      "NY.GDP.PCAP.CD": {
        "value": 25103.566,
        "year": 2024
      },
      "SN.ITK.DEFC.ZS": {
        "value": 2.5,
        "year": 2023
      },
      "AG.PRD.FOOD.XD": {
        "value": 111.71,
        "year": 2022
      }
    },
    "PRT": {
      "FP.CPI.TOTL.ZG": {
        "value": 2.416,
        "year": 2024
      },
      "NY.GDP.PCAP.CD": {
        "value": 29292.242,
        "year": 2024
      },
      "SN.ITK.DEFC.ZS": {
        "value": 2.5,
        "year": 2023
      },
      "AG.PRD.FOOD.XD": {
        "value": 110.34,
        "year": 2022
      }
    },
    "QAT": {
      "FP.CPI.TOTL.ZG": {
        "value": 1.267,
        "year": 2024
      },
      "NY.GDP.PCAP.CD": {
        "value": 76688.694,
        "year": 2024
      },
      "AG.PRD.FOOD.XD": {
        "value": 145.71,
        "year": 2022
      }
    },
    "ROU": {
      "FP.CPI.TOTL.ZG": {
        "value": 5.721,
        "year": 2024
      },
      "NY.GDP.PCAP.CD": {
        "value": 20080.21,
        "year": 2024
      },
      "SN.ITK.DEFC.ZS": {
        "value": 2.5,
        "year": 2023
      },
      "AG.PRD.FOOD.XD": {
        "value": 85.18,
        "year": 2022
      }
    },
    "RUS": {
      "FP.CPI.TOTL.ZG": {
        "value": 8.435,
        "year": 2024
      },
      "NY.GDP.PCAP.CD": {
        "value": 14889.019,
        "year": 2024
      },
      "SN.ITK.DEFC.ZS": {
        "value": 2.5,
        "year": 2023
      },
      "AG.PRD.FOOD.XD": {
        "value": 126.44,
        "year": 2022
      }
    },
    "RWA": {
      "FP.CPI.TOTL.ZG": {
        "value": 1.77,
        "year": 2024
      },
      "NY.GDP.PCAP.CD": {
        "value": 999.655,
        "year": 2024
      },
      "SN.ITK.DEFC.ZS": {
        "value": 24.4,
        "year": 2023
      },
      "AG.PRD.FOOD.XD": {
        "value": 117.31,
        "year": 2022
      }
    },
    "WSM": {
      "FP.CPI.TOTL.ZG": {
        "value": 2.172,
        "year": 2024
      },
      "NY.GDP.PCAP.CD": {
        "value": 5392.878,
        "year": 2024
      },
      "SN.ITK.DEFC.ZS": {
        "value": 3.6,
        "year": 2023
      },
      "AG.PRD.FOOD.XD": {
        "value": 83.05,
        "year": 2022
      }
    },
    "SMR": {
      "FP.CPI.TOTL.ZG": {
        "value": 1.242,
        "year": 2024
      }
    },
    "STP": {
      "FP.CPI.TOTL.ZG": {
        "value": 14.352,
        "year": 2024
      },
      "NY.GDP.PCAP.CD": {
        "value": 3490.569,
        "year": 2024
      },
      "SN.ITK.DEFC.ZS": {
        "value": 17.4,
        "year": 2023
      },
      "AG.PRD.FOOD.XD": {
        "value": 107.25,
        "year": 2022
      }
    },
    "SAU": {
      "FP.CPI.TOTL.ZG": {
        "value": 1.688,
        "year": 2024
      },
      "NY.GDP.PCAP.CD": {
        "value": 35121.663,
        "year": 2024
      },
      "SN.ITK.DEFC.ZS": {
        "value": 2.5,
        "year": 2023
      },
      "AG.PRD.FOOD.XD": {
        "value": 172.66,
        "year": 2022
      }
    },
    "SEN": {
      "FP.CPI.TOTL.ZG": {
        "value": 0.805,
        "year": 2024
      },
      "NY.GDP.PCAP.CD": {
        "value": 1773.218,
        "year": 2024
      },
      "SN.ITK.DEFC.ZS": {
        "value": 5.1,
        "year": 2023
      },
      "AG.PRD.FOOD.XD": {
        "value": 177.49,
        "year": 2022
      }
    },
    "SRB": {
      "FP.CPI.TOTL.ZG": {
        "value": 4.671,
        "year": 2024
      },
      "NY.GDP.PCAP.CD": {
        "value": 13679.207,
        "year": 2024
      },
      "SN.ITK.DEFC.ZS": {
        "value": 2.5,
        "year": 2023
      },
      "AG.PRD.FOOD.XD": {
        "value": 98.37,
        "year": 2022
      }
    },
    "SYC": {
      "FP.CPI.TOTL.ZG": {
        "value": 0.312,
        "year": 2024
      },
      "NY.GDP.PCAP.CD": {
        "value": 17858.823,
        "year": 2024
      },
      "SN.ITK.DEFC.ZS": {
        "value": 2.5,
        "year": 2023
      },
      "AG.PRD.FOOD.XD": {
        "value": 149.83,
        "year": 2022
      }
    },
    "SLE": {
      "FP.CPI.TOTL.ZG": {
        "value": 28.634,
        "year": 2024
      },
      "NY.GDP.PCAP.CD": {
        "value": 806.655,
        "year": 2024
      },
      "SN.ITK.DEFC.ZS": {
        "value": 24.1,
        "year": 2023
      },
      "AG.PRD.FOOD.XD": {
        "value": 104.72,
        "year": 2022
      }
    },
    "SGP": {
      "FP.CPI.TOTL.ZG": {
        "value": 2.39,
        "year": 2024
      },
      "NY.GDP.PCAP.CD": {
        "value": 90674.067,
        "year": 2024
      },
      "AG.PRD.FOOD.XD": {
        "value": 131.01,
        "year": 2022
      }
    },
    "SVK": {
      "FP.CPI.TOTL.ZG": {
        "value": 2.758,
        "year": 2024
      },
      "NY.GDP.PCAP.CD": {
        "value": 25992.675,
        "year": 2024
      },
      "SN.ITK.DEFC.ZS": {
        "value": 3.1,
        "year": 2023
      },
      "AG.PRD.FOOD.XD": {
        "value": 86.15,
        "year": 2022
      }
    },
    "SVN": {
      "FP.CPI.TOTL.ZG": {
        "value": 1.966,
        "year": 2024
      },
      "NY.GDP.PCAP.CD": {
        "value": 34301.032,
        "year": 2024
      },
      "SN.ITK.DEFC.ZS": {
        "value": 2.5,
        "year": 2023
      },
      "AG.PRD.FOOD.XD": {
        "value": 94.0,
        "year": 2022
      }
    },
    "SLB": {
      "FP.CPI.TOTL.ZG": {
        "value": 4.322,
        "year": 2024
      },
      "NY.GDP.PCAP.CD": {
        "value": 1933.555,
        "year": 2024
      },
      "SN.ITK.DEFC.ZS": {
        "value": 20.0,
        "year": 2023
      },
      "AG.PRD.FOOD.XD": {
        "value": 100.49,
        "year": 2022
      }
    },
    "ZAF": {
      "FP.CPI.TOTL.ZG": {
        "value": 4.361,
        "year": 2024
      },
      "NY.GDP.PCAP.CD": {
        "value": 6267.187,
        "year": 2024
      },
      "SN.ITK.DEFC.ZS": {
        "value": 10.0,
        "year": 2023
      },
      "AG.PRD.FOOD.XD": {
        "value": 113.24,
        "year": 2022
      }
    },
    "SSD": {
      "FP.CPI.TOTL.ZG": {
        "value": 91.441,
        "year": 2024
      },
      "SN.ITK.DEFC.ZS": {
        "value": 22.3,
        "year": 2023
      },
      "AG.PRD.FOOD.XD": {
        "value": 114.76,
        "year": 2022
      }
    },
    "ESP": {
      "FP.CPI.TOTL.ZG": {
        "value": 2.774,
        "year": 2024
      },
      "NY.GDP.PCAP.CD": {
        "value": 35326.768,
        "year": 2024
      },
      "SN.ITK.DEFC.ZS": {
        "value": 2.5,
        "year": 2023
      },
      "AG.PRD.FOOD.XD": {
        "value": 98.83,
        "year": 2022
      }
    },
    "LKA": {
      "FP.CPI.TOTL.ZG": {
        "value": -0.429,
        "year": 2024
      },
      "NY.GDP.PCAP.CD": {
        "value": 4515.568,
        "year": 2024
      },
      "SN.ITK.DEFC.ZS": {
        "value": 7.4,
        "year": 2023
      },
      "AG.PRD.FOOD.XD": {
        "value": 99.24,
        "year": 2022
      }
    },
    "LCA": {
      "FP.CPI.TOTL.ZG": {
        "value": -0.11,
        "year": 2024
      },
      "NY.GDP.PCAP.CD": {
        "value": 14181.63,
        "year": 2024
      },
      "AG.PRD.FOOD.XD": {
        "value": 90.59,
        "year": 2022
      }
    },
    "VCT": {
      "FP.CPI.TOTL.ZG": {
        "value": 3.628,
        "year": 2024
      },
      "NY.GDP.PCAP.CD": {
        "value": 11501.227,
        "year": 2024
      },
      "SN.ITK.DEFC.ZS": {
        "value": 6.1,
        "year": 2023
      },
      "AG.PRD.FOOD.XD": {
        "value": 101.11,
        "year": 2022
      }
    },
    "SUR": {
      "FP.CPI.TOTL.ZG": {
        "value": 16.23,
        "year": 2024
      },
      "NY.GDP.PCAP.CD": {
        "value": 6961.79,
        "year": 2024
      },
      "SN.ITK.DEFC.ZS": {
        "value": 9.7,
        "year": 2023
      },
      "AG.PRD.FOOD.XD": {
        "value": 87.89,
        "year": 2022
      }
    },
    "SWE": {
      "FP.CPI.TOTL.ZG": {
        "value": 2.836,
        "year": 2024
      },
      "NY.GDP.PCAP.CD": {
        "value": 57117.488,
        "year": 2024
      },
      "SN.ITK.DEFC.ZS": {
        "value": 2.5,
        "year": 2023
      },
      "AG.PRD.FOOD.XD": {
        "value": 101.15,
        "year": 2022
      }
    },
    "CHE": {
      "FP.CPI.TOTL.ZG": {
        "value": 1.062,
        "year": 2024
      },
      "NY.GDP.PCAP.CD": {
        "value": 103998.187,
        "year": 2024
      },
      "SN.ITK.DEFC.ZS": {
        "value": 2.5,
        "year": 2023
      },
      "AG.PRD.FOOD.XD": {
        "value": 97.39,
        "year": 2022
      }
    },
    "TZA": {
      "FP.CPI.TOTL.ZG": {
        "value": 3.057,
        "year": 2024
      },
      "NY.GDP.PCAP.CD": {
        "value": 1186.717,
        "year": 2024
      },
      "SN.ITK.DEFC.ZS": {
        "value": 20.2,
        "year": 2023
      },
      "AG.PRD.FOOD.XD": {
        "value": 109.9,
        "year": 2022
      }
    },
    "THA": {
      "FP.CPI.TOTL.ZG": {
        "value": 1.366,
        "year": 2024
      },
      "NY.GDP.PCAP.CD": {
        "value": 7346.62,
        "year": 2024
      },
      "SN.ITK.DEFC.ZS": {
        "value": 4.6,
        "year": 2023
      },
      "AG.PRD.FOOD.XD": {
        "value": 104.2,
        "year": 2022
      }
    },
    "TLS": {
      "FP.CPI.TOTL.ZG": {
        "value": 2.063,
        "year": 2024
      },
      "NY.GDP.PCAP.CD": {
        "value": 1331.971,
        "year": 2024
      },
      "SN.ITK.DEFC.ZS": {
        "value": 18.7,
        "year": 2023
      },
      "AG.PRD.FOOD.XD": {
        "value": 101.69,
        "year": 2022
      }
    },
    "TGO": {
      "FP.CPI.TOTL.ZG": {
        "value": 2.863,
        "year": 2024
      },
      "NY.GDP.PCAP.CD": {
        "value": 1119.382,
        "year": 2024
      },
      "SN.ITK.DEFC.ZS": {
        "value": 9.1,
        "year": 2023
      },
      "AG.PRD.FOOD.XD": {
        "value": 128.24,
        "year": 2022
      }
    },
    "TON": {
      "FP.CPI.TOTL.ZG": {
        "value": 3.231,
        "year": 2024
      },
      "AG.PRD.FOOD.XD": {
        "value": 97.78,
        "year": 2022
      }
    },
    "TTO": {
      "FP.CPI.TOTL.ZG": {
        "value": 0.527,
        "year": 2024
      },
      "NY.GDP.PCAP.CD": {
        "value": 18733.411,
        "year": 2024
      },
      "SN.ITK.DEFC.ZS": {
        "value": 11.2,
        "year": 2023
      },
      "AG.PRD.FOOD.XD": {
        "value": 93.08,
        "year": 2022
      }
    },
    "TUN": {
      "FP.CPI.TOTL.ZG": {
        "value": 7.207,
        "year": 2024
      },
      "NY.GDP.PCAP.CD": {
        "value": 4181.138,
        "year": 2024
      },
      "SN.ITK.DEFC.ZS": {
        "value": 3.0,
        "year": 2023
      },
      "AG.PRD.FOOD.XD": {
        "value": 109.55,
        "year": 2022
      }
    },
    "TUR": {
      "FP.CPI.TOTL.ZG": {
        "value": 58.506,
        "year": 2024
      },
      "NY.GDP.PCAP.CD": {
        "value": 15892.716,
        "year": 2024
      },
      "SN.ITK.DEFC.ZS": {
        "value": 2.5,
        "year": 2023
      },
      "AG.PRD.FOOD.XD": {
        "value": 128.92,
        "year": 2022
      }
    },
    "UGA": {
      "FP.CPI.TOTL.ZG": {
        "value": 3.323,
        "year": 2024
      },
      "NY.GDP.PCAP.CD": {
        "value": 1077.913,
        "year": 2024
      },
      "SN.ITK.DEFC.ZS": {
        "value": 22.0,
        "year": 2023
      },
      "AG.PRD.FOOD.XD": {
        "value": 135.53,
        "year": 2022
      }
    },
    "UKR": {
      "FP.CPI.TOTL.ZG": {
        "value": 6.502,
        "year": 2024
      },
      "NY.GDP.PCAP.CD": {
        "value": 5389.473,
        "year": 2024
      },
      "SN.ITK.DEFC.ZS": {
        "value": 6.9,
        "year": 2023
      },
      "AG.PRD.FOOD.XD": {
        "value": 87.83,
        "year": 2022
      }
    },
    "ARE": {
      "FP.CPI.TOTL.ZG": {
        "value": 1.663,
        "year": 2024
      },
      "NY.GDP.PCAP.CD": {
        "value": 50273.506,
        "year": 2024
      },
      "SN.ITK.DEFC.ZS": {
        "value": 2.5,
        "year": 2023
      },
      "AG.PRD.FOOD.XD": {
        "value": 124.86,
        "year": 2022
      }
    },
    "GBR": {
      "FP.CPI.TOTL.ZG": {
        "value": 3.272,
        "year": 2024
      },
      "NY.GDP.PCAP.CD": {
        "value": 53246.368,
        "year": 2024
      },
      "SN.ITK.DEFC.ZS": {
        "value": 2.5,
        "year": 2023
      },
      "AG.PRD.FOOD.XD": {
        "value": 101.24,
        "year": 2022
      }
    },
    "USA": {
      "FP.CPI.TOTL.ZG": {
        "value": 2.95,
        "year": 2024
      },
      "NY.GDP.PCAP.CD": {
        "value": 84534.041,
        "year": 2024
      },
      "SN.ITK.DEFC.ZS": {
        "value": 2.5,
        "year": 2023
      },
      "AG.PRD.FOOD.XD": {
        "value": 100.86,
        "year": 2022
      }
    },
    "URY": {
      "FP.CPI.TOTL.ZG": {
        "value": 4.849,
        "year": 2024
      },
      "NY.GDP.PCAP.CD": {
        "value": 23906.513,
        "year": 2024
      },
      "SN.ITK.DEFC.ZS": {
        "value": 2.5,
        "year": 2023
      },
      "AG.PRD.FOOD.XD": {
        "value": 97.82,
        "year": 2022
      }
    },
    "UZB": {
      "FP.CPI.TOTL.ZG": {
        "value": 9.628,
        "year": 2024
      },
      "NY.GDP.PCAP.CD": {
        "value": 3161.7,
        "year": 2024
      },
      "SN.ITK.DEFC.ZS": {
        "value": 2.5,
        "year": 2023
      },
      "AG.PRD.FOOD.XD": {
        "value": 114.43,
        "year": 2022
      },
      "SI.POV.NAHC": {
        "value": 5.8,
        "year": 2025
      }
    },
    "VNM": {
      "FP.CPI.TOTL.ZG": {
        "value": 3.621,
        "year": 2024
      },
      "NY.GDP.PCAP.CD": {
        "value": 4717.29,
        "year": 2024
      },
      "SN.ITK.DEFC.ZS": {
        "value": 5.3,
        "year": 2023
      },
      "AG.PRD.FOOD.XD": {
        "value": 113.65,
        "year": 2022
      }
    },
    "PSE": {
      "FP.CPI.TOTL.ZG": {
        "value": 53.669,
        "year": 2024
      },
      "NY.GDP.PCAP.CD": {
        "value": 2592.306,
        "year": 2024
      },
      "AG.PRD.FOOD.XD": {
        "value": 111.76,
        "year": 2022
      }
    },
    "ZMB": {
      "FP.CPI.TOTL.ZG": {
        "value": 14.986,
        "year": 2024
      },
      "NY.GDP.PCAP.CD": {
        "value": 1187.109,
        "year": 2024
      },
      "SN.ITK.DEFC.ZS": {
        "value": 37.2,
        "year": 2023
      },
      "AG.PRD.FOOD.XD": {
        "value": 119.91,
        "year": 2022
      }
    },
    "ARB": {
      "NY.GDP.PCAP.CD": {
        "value": 7583.812,
        "year": 2024
      },
      "SN.ITK.DEFC.ZS": {
        "value": 12.053,
        "year": 2023
      }
    },
    "CSS": {
      "NY.GDP.PCAP.CD": {
        "value": 19903.811,
        "year": 2024
      },
      "SN.ITK.DEFC.ZS": {
        "value": 7.725,
        "year": 2023
      }
    },
    "CEB": {
      "NY.GDP.PCAP.CD": {
        "value": 24604.807,
        "year": 2024
      },
      "SN.ITK.DEFC.ZS": {
        "value": 2.533,
        "year": 2023
      }
    },
    "EAR": {
      "NY.GDP.PCAP.CD": {
        "value": 4450.187,
        "year": 2024
      },
      "SN.ITK.DEFC.ZS": {
        "value": 10.573,
        "year": 2023
      }
    },
    "EAS": {
      "NY.GDP.PCAP.CD": {
        "value": 13405.736,
        "year": 2024
      },
      "SN.ITK.DEFC.ZS": {
        "value": 3.455,
        "year": 2023
      }
    },
    "EAP": {
      "NY.GDP.PCAP.CD": {
        "value": 10396.796,
        "year": 2024
      },
      "SN.ITK.DEFC.ZS": {
        "value": 3.487,
        "year": 2023
      }
    },
    "TEA": {
      "NY.GDP.PCAP.CD": {
        "value": 10513.953,
        "year": 2024
      },
      "SN.ITK.DEFC.ZS": {
        "value": 3.487,
        "year": 2023
      }
    },
    "EMU": {
      "NY.GDP.PCAP.CD": {
        "value": 46945.419,
        "year": 2024
      },
      "SN.ITK.DEFC.ZS": {
        "value": 2.509,
        "year": 2023
      }
    },
    "ECS": {
      "NY.GDP.PCAP.CD": {
        "value": 31555.521,
        "year": 2024
      },
      "SN.ITK.DEFC.ZS": {
        "value": 2.792,
        "year": 2023
      }
    },
    "ECA": {
      "NY.GDP.PCAP.CD": {
        "value": 9793.692,
        "year": 2024
      },
      "SN.ITK.DEFC.ZS": {
        "value": 3.577,
        "year": 2023
      }
    },
    "TEC": {
      "NY.GDP.PCAP.CD": {
        "value": 13337.439,
        "year": 2024
      },
      "SN.ITK.DEFC.ZS": {
        "value": 3.082,
        "year": 2023
      }
    },
    "EUU": {
      "NY.GDP.PCAP.CD": {
        "value": 43304.964,
        "year": 2024
      },
      "SN.ITK.DEFC.ZS": {
        "value": 2.507,
        "year": 2023
      }
    },
    "FCS": {
      "NY.GDP.PCAP.CD": {
        "value": 1527.958,
        "year": 2024
      },
      "SN.ITK.DEFC.ZS": {
        "value": 21.285,
        "year": 2023
      }
    },
    "HPC": {
      "NY.GDP.PCAP.CD": {
        "value": 1216.375,
        "year": 2024
      },
      "SN.ITK.DEFC.ZS": {
        "value": 23.016,
        "year": 2023
      }
    },
    "IBD": {
      "NY.GDP.PCAP.CD": {
        "value": 8219.913,
        "year": 2024
      },
      "SN.ITK.DEFC.ZS": {
        "value": 6.546,
        "year": 2023
      }
    },
    "IBT": {
      "NY.GDP.PCAP.CD": {
        "value": 6327.144,
        "year": 2024
      },
      "SN.ITK.DEFC.ZS": {
        "value": 9.926,
        "year": 2023
      }
    },
    "IDB": {
      "NY.GDP.PCAP.CD": {
        "value": 1650.638,
        "year": 2024
      },
      "SN.ITK.DEFC.ZS": {
        "value": 18.185,
        "year": 2023
      }
    },
    "IDX": {
      "NY.GDP.PCAP.CD": {
        "value": 1398.112,
        "year": 2024
      },
      "SN.ITK.DEFC.ZS": {
        "value": 20.011,
        "year": 2023
      }
    },
    "IDA": {
      "NY.GDP.PCAP.CD": {
        "value": 1485.922,
        "year": 2024
      },
      "SN.ITK.DEFC.ZS": {
        "value": 19.329,
        "year": 2023
      }
    },
    "LTE": {
      "NY.GDP.PCAP.CD": {
        "value": 12874.168,
        "year": 2024
      },
      "SN.ITK.DEFC.ZS": {
        "value": 2.897,
        "year": 2023
      }
    },
    "LCN": {
      "NY.GDP.PCAP.CD": {
        "value": 10737.646,
        "year": 2024
      },
      "SN.ITK.DEFC.ZS": {
        "value": 5.336,
        "year": 2023
      }
    },
    "LAC": {
      "NY.GDP.PCAP.CD": {
        "value": 10382.391,
        "year": 2024
      },
      "SN.ITK.DEFC.ZS": {
        "value": 5.435,
        "year": 2023
      }
    },
    "TLA": {
      "NY.GDP.PCAP.CD": {
        "value": 10474.281,
        "year": 2024
      },
      "SN.ITK.DEFC.ZS": {
        "value": 5.336,
        "year": 2023
      }
    },
    "LDC": {
      "NY.GDP.PCAP.CD": {
        "value": 1293.401,
        "year": 2024
      },
      "SN.ITK.DEFC.ZS": {
        "value": 20.669,
        "year": 2023
      }
    },
    "LMY": {
      "NY.GDP.PCAP.CD": {
        "value": 6002.451,
        "year": 2024
      },
      "SN.ITK.DEFC.ZS": {
        "value": 10.029,
        "year": 2023
      }
    },
    "MEA": {
      "NY.GDP.PCAP.CD": {
        "value": 6265.444,
        "year": 2024
      },
      "SN.ITK.DEFC.ZS": {
        "value": 12.653,
        "year": 2023
      }
    },
    "MNA": {
      "NY.GDP.PCAP.CD": {
        "value": 2971.055,
        "year": 2024
      },
      "SN.ITK.DEFC.ZS": {
        "value": 13.584,
        "year": 2023
      }
    },
    "TMN": {
      "NY.GDP.PCAP.CD": {
        "value": 2973.775,
        "year": 2024
      },
      "SN.ITK.DEFC.ZS": {
        "value": 13.584,
        "year": 2023
      }
    },
    "MIC": {
      "NY.GDP.PCAP.CD": {
        "value": 6554.371,
        "year": 2024
      },
      "SN.ITK.DEFC.ZS": {
        "value": 8.536,
        "year": 2023
      }
    },
    "NAC": {
      "NY.GDP.PCAP.CD": {
        "value": 81275.844,
        "year": 2024
      },
      "SN.ITK.DEFC.ZS": {
        "value": 2.5,
        "year": 2023
      }
    },
    "OED": {
      "NY.GDP.PCAP.CD": {
        "value": 48322.164,
        "year": 2024
      },
      "SN.ITK.DEFC.ZS": {
        "value": 2.581,
        "year": 2023
      }
    },
    "OSS": {
      "NY.GDP.PCAP.CD": {
        "value": 16094.127,
        "year": 2024
      },
      "SN.ITK.DEFC.ZS": {
        "value": 9.519,
        "year": 2023
      }
    },
    "PSS": {
      "NY.GDP.PCAP.CD": {
        "value": 4453.586,
        "year": 2024
      },
      "SN.ITK.DEFC.ZS": {
        "value": 10.826,
        "year": 2023
      }
    },
    "PST": {
      "NY.GDP.PCAP.CD": {
        "value": 55644.315,
        "year": 2024
      },
      "SN.ITK.DEFC.ZS": {
        "value": 2.681,
        "year": 2023
      }
    },
    "PRE": {
      "NY.GDP.PCAP.CD": {
        "value": 1366.066,
        "year": 2024
      },
      "SN.ITK.DEFC.ZS": {
        "value": 23.396,
        "year": 2023
      }
    },
    "SST": {
      "NY.GDP.PCAP.CD": {
        "value": 15383.343,
        "year": 2024
      },
      "SN.ITK.DEFC.ZS": {
        "value": 9.315,
        "year": 2023
      }
    },
    "SAS": {
      "NY.GDP.PCAP.CD": {
        "value": 2690.079,
        "year": 2024
      },
      "SN.ITK.DEFC.ZS": {
        "value": 11.654,
        "year": 2023
      }
    },
    "TSA": {
      "NY.GDP.PCAP.CD": {
        "value": 2690.079,
        "year": 2024
      },
      "SN.ITK.DEFC.ZS": {
        "value": 11.654,
        "year": 2023
      }
    },
    "SSF": {
      "NY.GDP.PCAP.CD": {
        "value": 1532.928,
        "year": 2024
      },
      "SN.ITK.DEFC.ZS": {
        "value": 21.882,
        "year": 2023
      }
    },
    "SSA": {
      "NY.GDP.PCAP.CD": {
        "value": 1576.692,
        "year": 2024
      },
      "SN.ITK.DEFC.ZS": {
        "value": 22.149,
        "year": 2023
      }
    },
    "TSS": {
      "NY.GDP.PCAP.CD": {
        "value": 1532.928,
        "year": 2024
      },
      "SN.ITK.DEFC.ZS": {
        "value": 21.882,
        "year": 2023
      }
    },
    "WLD": {
      "NY.GDP.PCAP.CD": {
        "value": 13631.204,
        "year": 2024
      },
      "SN.ITK.DEFC.ZS": {
        "value": 8.5,
        "year": 2023
      }
    },
    "AND": {
      "NY.GDP.PCAP.CD": {
        "value": 49303.649,
        "year": 2024
      }
    },
    "ABW": {
      "NY.GDP.PCAP.CD": {
        "value": 39498.594,
        "year": 2024
      }
    },
    "BMU": {
      "NY.GDP.PCAP.CD": {
        "value": 142855.375,
        "year": 2024
      }
    },
    "COD": {
      "NY.GDP.PCAP.CD": {
        "value": 649.383,
        "year": 2024
      },
      "SN.ITK.DEFC.ZS": {
        "value": 38.5,
        "year": 2023
      },
      "AG.PRD.FOOD.XD": {
        "value": 122.79,
        "year": 2022
      }
    },
    "CUW": {
      "NY.GDP.PCAP.CD": {
        "value": 22832.895,
        "year": 2024
      }
    },
    "SWZ": {
      "NY.GDP.PCAP.CD": {
        "value": 3909.559,
        "year": 2024
      },
      "SN.ITK.DEFC.ZS": {
        "value": 14.7,
        "year": 2023
      },
      "AG.PRD.FOOD.XD": {
        "value": 105.96,
        "year": 2022
      }
    },
    "FRO": {
      "NY.GDP.PCAP.CD": {
        "value": 74119.661,
        "year": 2024
      },
      "AG.PRD.FOOD.XD": {
        "value": 106.62,
        "year": 2022
      }
    },
    "PYF": {
      "NY.GDP.PCAP.CD": {
        "value": 22439.884,
        "year": 2024
      },
      "SN.ITK.DEFC.ZS": {
        "value": 3.8,
        "year": 2023
      },
      "AG.PRD.FOOD.XD": {
        "value": 102.81,
        "year": 2022
      }
    },
    "MHL": {
      "NY.GDP.PCAP.CD": {
        "value": 7726.337,
        "year": 2024
      },
      "AG.PRD.FOOD.XD": {
        "value": 90.84,
        "year": 2022
      }
    },
    "FSM": {
      "NY.GDP.PCAP.CD": {
        "value": 4166.005,
        "year": 2024
      },
      "AG.PRD.FOOD.XD": {
        "value": 121.63,
        "year": 2022
      }
    },
    "MCO": {
      "NY.GDP.PCAP.CD": {
        "value": 288001.433,
        "year": 2024
      }
    },
    "MMR": {
      "NY.GDP.PCAP.CD": {
        "value": 1359.05,
        "year": 2024
      },
      "SN.ITK.DEFC.ZS": {
        "value": 5.4,
        "year": 2023
      },
      "AG.PRD.FOOD.XD": {
        "value": 76.96,
        "year": 2022
      }
    },
    "NRU": {
      "NY.GDP.PCAP.CD": {
        "value": 13609.159,
        "year": 2024
      },
      "AG.PRD.FOOD.XD": {
        "value": 99.71,
        "year": 2022
      }
    },
    "NCL": {
      "NY.GDP.PCAP.CD": {
        "value": 29213.192,
        "year": 2024
      },
      "SN.ITK.DEFC.ZS": {
        "value": 4.9,
        "year": 2023
      },
      "AG.PRD.FOOD.XD": {
        "value": 94.76,
        "year": 2022
      }
    },
    "PRI": {
      "NY.GDP.PCAP.CD": {
        "value": 39343.715,
        "year": 2024
      },
      "AG.PRD.FOOD.XD": {
        "value": 95.25,
        "year": 2022
      }
    },
    "SXM": {
      "NY.GDP.PCAP.CD": {
        "value": 41472.587,
        "year": 2024
      }
    },
    "SOM": {
      "NY.GDP.PCAP.CD": {
        "value": 629.539,
        "year": 2024
      },
      "SN.ITK.DEFC.ZS": {
        "value": 53.2,
        "year": 2023
      },
      "AG.PRD.FOOD.XD": {
        "value": 98.94,
        "year": 2022
      }
    },
    "KNA": {
      "NY.GDP.PCAP.CD": {
        "value": 23960.653,
        "year": 2024
      },
      "AG.PRD.FOOD.XD": {
        "value": 115.11,
        "year": 2022
      }
    },
    "SDN": {
      "NY.GDP.PCAP.CD": {
        "value": 984.608,
        "year": 2024
      },
      "AG.PRD.FOOD.XD": {
        "value": 116.41,
        "year": 2022
      }
    },
    "TJK": {
      "NY.GDP.PCAP.CD": {
        "value": 1341.202,
        "year": 2024
      },
      "SN.ITK.DEFC.ZS": {
        "value": 8.4,
        "year": 2023
      },
      "AG.PRD.FOOD.XD": {
        "value": 150.12,
        "year": 2022
      }
    },
    "TKM": {
      "NY.GDP.PCAP.CD": {
        "value": 6856.658,
        "year": 2024
      },
      "SN.ITK.DEFC.ZS": {
        "value": 4.3,
        "year": 2023
      },
      "AG.PRD.FOOD.XD": {
        "value": 112.03,
        "year": 2022
      }
    },
    "TCA": {
      "NY.GDP.PCAP.CD": {
        "value": 37506.78,
        "year": 2024
      }
    },
    "VUT": {
      "NY.GDP.PCAP.CD": {
        "value": 3410.77,
        "year": 2024
      },
      "SN.ITK.DEFC.ZS": {
        "value": 7.2,
        "year": 2023
      },
      "AG.PRD.FOOD.XD": {
        "value": 82.96,
        "year": 2022
      }
    },
    "VEN": {
      "NY.GDP.PCAP.CD": {
        "value": 4217.591,
        "year": 2024
      },
      "SN.ITK.DEFC.ZS": {
        "value": 5.9,
        "year": 2023
      },
      "AG.PRD.FOOD.XD": {
        "value": 89.88,
        "year": 2022
      }
    },
    "ZWE": {
      "NY.GDP.PCAP.CD": {
        "value": 2497.203,
        "year": 2024
      },
      "SN.ITK.DEFC.ZS": {
        "value": 19.7,
        "year": 2023
      },
      "AG.PRD.FOOD.XD": {
        "value": 121.68,
        "year": 2022
      }
    },
    "SYR": {
      "SN.ITK.DEFC.ZS": {
        "value": 39.0,
        "year": 2023
      },
      "AG.PRD.FOOD.XD": {
        "value": 96.98,
        "year": 2022
      }
    },
    "CUB": {
      "AG.PRD.FOOD.XD": {
        "value": 71.39,
        "year": 2022
      }
    },
    "ERI": {
      "AG.PRD.FOOD.XD": {
        "value": 106.08,
        "year": 2022
      }
    },
    "PRK": {
      "AG.PRD.FOOD.XD": {
        "value": 92.69,
        "year": 2022
      }
    },
    "TUV": {
      "AG.PRD.FOOD.XD": {
        "value": 110.82,
        "year": 2022
      }
    },
    "YEM": {
      "AG.PRD.FOOD.XD": {
        "value": 118.29,
        "year": 2022
      }
    }
  }
}